odoo/addons/l10n_br_hr/README.rst
odoo/addons/l10n_br_hr/__init__.py
odoo/addons/l10n_br_hr/__manifest__.py
odoo/addons/l10n_br_hr/data/hr_deficiency_data.xml
odoo/addons/l10n_br_hr/data/hr_ethnicity_data.xml
odoo/addons/l10n_br_hr/data/l10n_br_hr.cbo.csv
odoo/addons/l10n_br_hr/i18n/l10n_br_hr.pot
odoo/addons/l10n_br_hr/i18n/pt_BR.po
odoo/addons/l10n_br_hr/models/__init__.py
odoo/addons/l10n_br_hr/models/data_abstract.py
odoo/addons/l10n_br_hr/models/hr_civil_certificate_type.py
odoo/addons/l10n_br_hr/models/hr_deficiency.py
odoo/addons/l10n_br_hr/models/hr_employee.py
odoo/addons/l10n_br_hr/models/hr_ethnicity.py
odoo/addons/l10n_br_hr/models/hr_identity_type.py
odoo/addons/l10n_br_hr/models/hr_job.py
odoo/addons/l10n_br_hr/models/l10n_br_hr_cbo.py
odoo/addons/l10n_br_hr/models/res_company.py
odoo/addons/l10n_br_hr/models/res_partner.py
odoo/addons/l10n_br_hr/readme/CONFIGURE.md
odoo/addons/l10n_br_hr/readme/CONTRIBUTORS.md
odoo/addons/l10n_br_hr/readme/DESCRIPTION.md
odoo/addons/l10n_br_hr/readme/INSTALL.md
odoo/addons/l10n_br_hr/readme/ROADMAP.md
odoo/addons/l10n_br_hr/readme/USAGE.md
odoo/addons/l10n_br_hr/security/ir.model.access.csv
odoo/addons/l10n_br_hr/static/description/icon.png
odoo/addons/l10n_br_hr/static/description/index.html
odoo/addons/l10n_br_hr/tests/__init__.py
odoo/addons/l10n_br_hr/tests/test_l10n_br_hr.py
odoo/addons/l10n_br_hr/views/hr_employee_view.xml
odoo/addons/l10n_br_hr/views/hr_job_view.xml
odoo/addons/l10n_br_hr/views/inherited_hr_contract.xml
odoo/addons/l10n_br_hr/views/l10n_br_hr_cbo_view.xml
odoo/addons/l10n_br_hr/views/res_company_view.xml
odoo/addons/l10n_br_hr/views/res_partner_view.xml
odoo_addon_l10n_br_hr-18.0.1.2.0.dist-info/METADATA
odoo_addon_l10n_br_hr-18.0.1.2.0.dist-info/WHEEL
odoo_addon_l10n_br_hr-18.0.1.2.0.dist-info/top_level.txt
odoo_addon_l10n_br_hr-18.0.1.2.0.dist-info/RECORD
