Metadata-Version: 2.1
Name: odoo-addon-l10n_br_hr
Version: 18.0.1.2.0
Requires-Python: >=3.10
Requires-Dist: erpbrasil.base
Requires-Dist: odoo-addon-hr_employee_relative==18.0.*
Requires-Dist: odoo-addon-l10n_br_base==18.0.*
Requires-Dist: odoo==18.0.*
Summary: Brazilian Localization HR
Home-page: https://github.com/OCA/l10n-brazil
License: AGPL-3
Author: KMEE, Odoo Community Association (OCA)
Author-email: support@odoo-community.org
Classifier: Programming Language :: Python
Classifier: Framework :: Odoo
Classifier: Framework :: Odoo :: 18.0
Classifier: License :: OSI Approved :: GNU Affero General Public License v3
